hellologger/__init__.py
hellologger/const.py
hellologger-0.2.2.post2.dist-info/LICENSE
hellologger-0.2.2.post2.dist-info/METADATA
hellologger-0.2.2.post2.dist-info/WHEEL
hellologger-0.2.2.post2.dist-info/RECORD
