Metadata-Version: 2.1
Name: hellologger
Version: 0.2.2.post2
Summary: 
Home-page: https://github.com/OSMChina/Yuheng
License: MIT
Author: 快乐的老鼠宝宝
Author-email: laoshubaby@protonmail.com
Requires-Python: >=3.11,<4.0
Classifier: License :: OSI Approved :: MIT License
Classifier: Operating System :: OS Independent
Classifier: Programming Language :: Python :: 3
Classifier: Programming Language :: Python :: 3.11
Classifier: Programming Language :: Python :: 3.12
Requires-Dist: loguru (>=0.7.2,<0.8.0)
Project-URL: Repository, https://github.com/OSMChina/Yuheng
